odan.py
odan-0.0.1.dist-info/LICENCE.txt
odan-0.0.1.dist-info/METADATA
odan-0.0.1.dist-info/WHEEL
odan-0.0.1.dist-info/top_level.txt
odan-0.0.1.dist-info/RECORD
