Metadata-Version: 2.1
Name: odan
Version: 0.0.1
Summary: Odoo deployment and network
Home-page: https://github.com/vpcarlos/odan
Author: Carlos Valdivia
Author-email: vpcarlos97@gmail.com
License: unlicensed
Platform: UNKNOWN
Requires-Dist: click (>=7.0)
Provides-Extra: dev
Requires-Dist: pytest (>=3.7) ; extra == 'dev'
